dones
