Metadata-Version: 1.1
Name: dones
Version: 0.2.0
Summary: Track what keys are "done" using MySQL to implement a simple key-store.
Home-page: https://github.com/todddeluca/dones
Author: Todd Francis DeLuca
Author-email: todddeluca@yahoo.com
License: MIT
Keywords: mysql keystore batch queue LSF
Platform: UNKNOWN
Classifier: License :: OSI Approved :: MIT License
Classifier: Development Status :: 3 - Alpha
Classifier: Programming Language :: Python :: 2
Classifier: Programming Language :: Python :: 2.7
